comment_remover_cli-1.2.1.dist-info/licenses/LICENSE
comms/__init__.py
comms/cli.py
comms/config.py
comms/core.py
comms/demo.py
comms/undo.py
tests/__init__.py
tests/test_comms.py
comment_remover_cli-1.2.1.dist-info/METADATA
comment_remover_cli-1.2.1.dist-info/WHEEL
comment_remover_cli-1.2.1.dist-info/entry_points.txt
comment_remover_cli-1.2.1.dist-info/top_level.txt
comment_remover_cli-1.2.1.dist-info/RECORD
