Metadata-Version: 2.4
Name: comment-remover-cli
Version: 1.2.1
Summary: High-accuracy comment removal tool for 20+ programming languages with beautiful CLI
Home-page: https://github.com/guider23/Comms
Author: guider23
Author-email: sofiyasenthilkumar@gmail.com
Project-URL: Bug Tracker, https://github.com/guider23/Comms/issues
Project-URL: Documentation, https://github.com/guider23/Comms#readme
Project-URL: Source Code, https://github.com/guider23/Comms
Keywords: comments removal programming development tools parsing
Classifier: Development Status :: 5 - Production/Stable
Classifier: Intended Audience :: Developers
Classifier: License :: OSI Approved :: MIT License
Classifier: Programming Language :: Python :: 3
Classifier: Programming Language :: Python :: 3.6
Classifier: Programming Language :: Python :: 3.7
Classifier: Programming Language :: Python :: 3.8
Classifier: Programming Language :: Python :: 3.9
Classifier: Programming Language :: Python :: 3.10
Classifier: Programming Language :: Python :: 3.11
Classifier: Programming Language :: Python :: 3.12
Classifier: Operating System :: OS Independent
Classifier: Topic :: Software Development :: Code Generators
Classifier: Topic :: Software Development :: Pre-processors
Classifier: Topic :: Text Processing :: Filters
Classifier: Topic :: Utilities
Requires-Python: >=3.6
License-File: LICENSE
Provides-Extra: dev
Requires-Dist: pytest>=6.0; extra == "dev"
Requires-Dist: black; extra == "dev"
Requires-Dist: flake8; extra == "dev"
Requires-Dist: mypy; extra == "dev"
Dynamic: author
Dynamic: author-email
Dynamic: classifier
Dynamic: description
Dynamic: description-content-type
Dynamic: home-page
Dynamic: keywords
Dynamic: license-file
Dynamic: project-url
Dynamic: provides-extra
Dynamic: requires-python
Dynamic: summary
